README.md
setup.py
wumpus/__init__.py
wumpus/errors.py
wumpus/utils.py
wumpus.py.egg-info/PKG-INFO
wumpus.py.egg-info/SOURCES.txt
wumpus.py.egg-info/dependency_links.txt
wumpus.py.egg-info/requires.txt
wumpus.py.egg-info/top_level.txt
wumpus/core/__init__.py
wumpus/core/client.py
wumpus/core/connection.py
wumpus/core/enums.py
wumpus/core/events.py
wumpus/core/gateway.py
wumpus/core/http.py
wumpus/core/manager.py
wumpus/models/__init__.py
wumpus/models/asset.py
wumpus/models/color.py
wumpus/models/embed.py
wumpus/models/emoji.py
wumpus/models/guild.py
wumpus/models/messageable.py
wumpus/models/objects.py
wumpus/models/user.py
wumpus/typings/__init__.py
wumpus/typings/core.py
wumpus/typings/payloads.py